john_filler/__init__.py
john_filler/main.py
john_filler/nafuka/__init__.py
john_filler/nafuka/filler.py
john_filler-0.1.4.dist-info/entry_points.txt
john_filler-0.1.4.dist-info/WHEEL
john_filler-0.1.4.dist-info/METADATA
john_filler-0.1.4.dist-info/RECORD
