Metadata-Version: 2.1
Name: john-filler
Version: 0.1.4
Summary: John team's filler
Author: John team
Requires-Python: >=3.8,<4.0
Classifier: Programming Language :: Python :: 3
Classifier: Programming Language :: Python :: 3.8
Classifier: Programming Language :: Python :: 3.9
